{
  "timestamp": "2026-03-13T04:02:18Z",
  "lookback_seconds": 3600,
  "tokens": {
    "UAI": {
      "deployments": [
        {
          "chain": "bsc",
          "contract": "0x3e5d4f8aee0d9b3082d5f6da5d6e225d17ba9ea0",
          "exchange_flows": {
            "Binance": {
              "inflow": 0.0,
              "outflow": 4135.5696,
              "net_flow": -4135.5696,
              "inflow_tx_count": 0,
              "outflow_tx_count": 3
            }
          }
        }
      ],
      "total_inflow": 0.0,
      "total_outflow": 4135.5696,
      "net_flow": -4135.5696
    },
    "BIRB": {
      "deployments": [
        {
          "chain": "solana",
          "contract": "G7vQWurMkMMm2dU3iZpXYFTHT9Biio4F4gZCrwFpKNwG",
          "exchange_flows": {
            "Bybit": {
              "inflow": 0.0,
              "outflow": 76498.0672,
              "net_flow": -76498.0672,
              "inflow_tx_count": 0,
              "outflow_tx_count": 1
            },
            "Coinbase": {
              "inflow": 76498.0672,
              "outflow": 0.0,
              "net_flow": 76498.0672,
              "inflow_tx_count": 1,
              "outflow_tx_count": 0
            },
            "Gate.io": {
              "inflow": 5114.0,
              "outflow": 0.0,
              "net_flow": 5114.0,
              "inflow_tx_count": 1,
              "outflow_tx_count": 0
            }
          }
        }
      ],
      "total_inflow": 81612.0672,
      "total_outflow": 76498.0672,
      "net_flow": 5114.0
    },
    "AZTEC": {
      "deployments": [
        {
          "chain": "ethereum",
          "contract": "0xA27EC0006e59f245217Ff08CD52A7E8b169E62D2",
          "exchange_flows": {
            "Bybit": {
              "inflow": 81750.4693,
              "outflow": 0.0,
              "net_flow": 81750.4693,
              "inflow_tx_count": 2,
              "outflow_tx_count": 0
            },
            "Gate.io": {
              "inflow": 1866688.772,
              "outflow": 337942.1871,
              "net_flow": 1528746.5849,
              "inflow_tx_count": 2,
              "outflow_tx_count": 2
            }
          }
        }
      ],
      "total_inflow": 1948439.2413,
      "total_outflow": 337942.1871,
      "net_flow": 1610497.0542
    },
    "TRIA": {
      "deployments": [
        {
          "chain": "ethereum",
          "contract": "0x228bec415ade4b61d7caf0adf8c91eac587ba369",
          "exchange_flows": {
            "Bitget": {
              "inflow": 124629.1996,
              "outflow": 0.0,
              "net_flow": 124629.1996,
              "inflow_tx_count": 2,
              "outflow_tx_count": 0
            },
            "Bybit": {
              "inflow": 145768.8086,
              "outflow": 0.0,
              "net_flow": 145768.8086,
              "inflow_tx_count": 7,
              "outflow_tx_count": 0
            },
            "MEXC": {
              "inflow": 13537.7309,
              "outflow": 0.0,
              "net_flow": 13537.7309,
              "inflow_tx_count": 3,
              "outflow_tx_count": 0
            }
          }
        },
        {
          "chain": "bsc",
          "contract": "0xb0b92de23baa85fb06208277e925ced53edab482",
          "exchange_flows": {
            "Binance": {
              "inflow": 1836.3731,
              "outflow": 800.0,
              "net_flow": 1036.3731,
              "inflow_tx_count": 1,
              "outflow_tx_count": 1
            }
          }
        }
      ],
      "total_inflow": 285772.1122,
      "total_outflow": 800.0,
      "net_flow": 284972.1122
    },
    "SKR": {
      "deployments": [
        {
          "chain": "solana",
          "contract": "SKRbvo6Gf7GondiT3BbTfuRDPqLWei4j2Qy2NPGZhW3",
          "exchange_flows": {
            "Bitget": {
              "inflow": 0.0,
              "outflow": 241740.3234,
              "net_flow": -241740.3234,
              "inflow_tx_count": 0,
              "outflow_tx_count": 1
            }
          }
        }
      ],
      "total_inflow": 0.0,
      "total_outflow": 241740.3234,
      "net_flow": -241740.3234
    },
    "GWEI": {
      "deployments": [
        {
          "chain": "ethereum",
          "contract": "0x2798b1cc5a993085e8a9d46e80499f1b63f42204",
          "exchange_flows": {
            "Bitget": {
              "inflow": 179616.8166,
              "outflow": 27094.3745,
              "net_flow": 152522.4422,
              "inflow_tx_count": 1,
              "outflow_tx_count": 1
            },
            "Coinbase": {
              "inflow": 259967.52,
              "outflow": 194123.3518,
              "net_flow": 65844.1682,
              "inflow_tx_count": 2,
              "outflow_tx_count": 3
            },
            "Gate.io": {
              "inflow": 529607.5849,
              "outflow": 594567.7,
              "net_flow": -64960.1151,
              "inflow_tx_count": 3,
              "outflow_tx_count": 6
            },
            "MEXC": {
              "inflow": 1597.013,
              "outflow": 262647.0,
              "net_flow": -261049.987,
              "inflow_tx_count": 2,
              "outflow_tx_count": 5
            }
          }
        }
      ],
      "total_inflow": 970788.9345,
      "total_outflow": 1078432.4263,
      "net_flow": -107643.4918
    },
    "SPACE": {
      "deployments": [
        {
          "chain": "ethereum",
          "contract": "0x87acFA3fD7A6e0d48677D070644D76905C2bDC00",
          "exchange_flows": {}
        },
        {
          "chain": "bsc",
          "contract": "0x87acFA3fD7A6e0d48677D070644D76905C2bDC00",
          "exchange_flows": {}
        }
      ],
      "total_inflow": 0,
      "total_outflow": 0,
      "net_flow": 0
    },
    "PUMP": {
      "deployments": [
        {
          "chain": "solana",
          "contract": "pumpCmXqMfrsAkQ5r49WcJnRayYRqmXz6ae8H7H9Dfn",
          "exchange_flows": {
            "Binance": {
              "inflow": 67599610.447,
              "outflow": 2126692.35,
              "net_flow": 65472918.097,
              "inflow_tx_count": 6,
              "outflow_tx_count": 1
            },
            "Bitget": {
              "inflow": 0.0,
              "outflow": 4066714.5789,
              "net_flow": -4066714.5789,
              "inflow_tx_count": 0,
              "outflow_tx_count": 2
            },
            "Bitvavo": {
              "inflow": 10748476.0,
              "outflow": 0.0,
              "net_flow": 10748476.0,
              "inflow_tx_count": 1,
              "outflow_tx_count": 0
            },
            "BtcTurk Cold Wallet (3B7X...ei9z)": {
              "inflow": 0.0,
              "outflow": 95297088.6739,
              "net_flow": -95297088.6739,
              "inflow_tx_count": 0,
              "outflow_tx_count": 1
            },
            "Bybit": {
              "inflow": 448873.0,
              "outflow": 110448383.0726,
              "net_flow": -109999510.0726,
              "inflow_tx_count": 1,
              "outflow_tx_count": 2
            },
            "Coinbase": {
              "inflow": 7149800.5163,
              "outflow": 0.0,
              "net_flow": 7149800.5163,
              "inflow_tx_count": 3,
              "outflow_tx_count": 0
            },
            "Upbit": {
              "inflow": 2126692.35,
              "outflow": 0.0,
              "net_flow": 2126692.35,
              "inflow_tx_count": 1,
              "outflow_tx_count": 0
            },
            "Wintermute": {
              "inflow": 0.0,
              "outflow": 969901.917,
              "net_flow": -969901.917,
              "inflow_tx_count": 0,
              "outflow_tx_count": 6
            }
          }
        }
      ],
      "total_inflow": 88073452.3133,
      "total_outflow": 212908780.5924,
      "net_flow": -124835328.2791
    }
  }
}