{
  "timestamp": "2026-03-13T14:35:21Z",
  "lookback_seconds": 3600,
  "tokens": {
    "UAI": {
      "deployments": [
        {
          "chain": "bsc",
          "contract": "0x3e5d4f8aee0d9b3082d5f6da5d6e225d17ba9ea0",
          "exchange_flows": {
            "Binance": {
              "inflow": 355.3513,
              "outflow": 148.7134,
              "net_flow": 206.6379,
              "inflow_tx_count": 3,
              "outflow_tx_count": 1
            },
            "Gate.io": {
              "inflow": 0.0,
              "outflow": 86106.02,
              "net_flow": -86106.02,
              "inflow_tx_count": 0,
              "outflow_tx_count": 2
            }
          }
        }
      ],
      "total_inflow": 355.3513,
      "total_outflow": 86254.7334,
      "net_flow": -85899.3821
    },
    "BIRB": {
      "deployments": [
        {
          "chain": "solana",
          "contract": "G7vQWurMkMMm2dU3iZpXYFTHT9Biio4F4gZCrwFpKNwG",
          "exchange_flows": {
            "Bybit": {
              "inflow": 335788.9628,
              "outflow": 144006.0,
              "net_flow": 191782.9628,
              "inflow_tx_count": 4,
              "outflow_tx_count": 1
            },
            "Coinbase": {
              "inflow": 0.0,
              "outflow": 35104.5,
              "net_flow": -35104.5,
              "inflow_tx_count": 0,
              "outflow_tx_count": 1
            },
            "Gate.io": {
              "inflow": 4072.0,
              "outflow": 0.0,
              "net_flow": 4072.0,
              "inflow_tx_count": 1,
              "outflow_tx_count": 0
            },
            "HTX": {
              "inflow": 1240.6131,
              "outflow": 0.0,
              "net_flow": 1240.6131,
              "inflow_tx_count": 5,
              "outflow_tx_count": 0
            },
            "KuCoin": {
              "inflow": 144006.0,
              "outflow": 144006.3,
              "net_flow": -0.3,
              "inflow_tx_count": 1,
              "outflow_tx_count": 1
            }
          }
        }
      ],
      "total_inflow": 485107.5759,
      "total_outflow": 323116.8,
      "net_flow": 161990.7759
    },
    "AZTEC": {
      "deployments": [
        {
          "chain": "ethereum",
          "contract": "0xA27EC0006e59f245217Ff08CD52A7E8b169E62D2",
          "exchange_flows": {
            "Bybit": {
              "inflow": 0.0,
              "outflow": 2574721.5295,
              "net_flow": -2574721.5295,
              "inflow_tx_count": 0,
              "outflow_tx_count": 5
            },
            "Coinbase": {
              "inflow": 979573.0,
              "outflow": 0.0,
              "net_flow": 979573.0,
              "inflow_tx_count": 1,
              "outflow_tx_count": 0
            },
            "Gate.io": {
              "inflow": 1042007.0,
              "outflow": 428705.7285,
              "net_flow": 613301.2715,
              "inflow_tx_count": 1,
              "outflow_tx_count": 4
            },
            "MEXC": {
              "inflow": 0.0,
              "outflow": 145746.24,
              "net_flow": -145746.24,
              "inflow_tx_count": 0,
              "outflow_tx_count": 3
            }
          }
        }
      ],
      "total_inflow": 2021580.0,
      "total_outflow": 3149173.498,
      "net_flow": -1127593.498
    },
    "TRIA": {
      "deployments": [
        {
          "chain": "ethereum",
          "contract": "0x228bec415ade4b61d7caf0adf8c91eac587ba369",
          "exchange_flows": {
            "Bitvavo": {
              "inflow": 181646.89,
              "outflow": 157586.0,
              "net_flow": 24060.89,
              "inflow_tx_count": 1,
              "outflow_tx_count": 1
            },
            "Coinbase": {
              "inflow": 0.0,
              "outflow": 2452.7881,
              "net_flow": -2452.7881,
              "inflow_tx_count": 0,
              "outflow_tx_count": 1
            },
            "MEXC": {
              "inflow": 0.0,
              "outflow": 62691.49,
              "net_flow": -62691.49,
              "inflow_tx_count": 0,
              "outflow_tx_count": 3
            }
          }
        },
        {
          "chain": "bsc",
          "contract": "0xb0b92de23baa85fb06208277e925ced53edab482",
          "exchange_flows": {
            "Binance": {
              "inflow": 0.0,
              "outflow": 41089.4148,
              "net_flow": -41089.4148,
              "inflow_tx_count": 0,
              "outflow_tx_count": 3
            }
          }
        }
      ],
      "total_inflow": 181646.89,
      "total_outflow": 263819.6929,
      "net_flow": -82172.8029
    },
    "SKR": {
      "deployments": [
        {
          "chain": "solana",
          "contract": "SKRbvo6Gf7GondiT3BbTfuRDPqLWei4j2Qy2NPGZhW3",
          "exchange_flows": {
            "Bybit": {
              "inflow": 0.0,
              "outflow": 270746.68,
              "net_flow": -270746.68,
              "inflow_tx_count": 0,
              "outflow_tx_count": 1
            },
            "Coinbase": {
              "inflow": 10784.7282,
              "outflow": 6994.3932,
              "net_flow": 3790.335,
              "inflow_tx_count": 1,
              "outflow_tx_count": 1
            },
            "Indodax": {
              "inflow": 0.0,
              "outflow": 2475.118,
              "net_flow": -2475.118,
              "inflow_tx_count": 0,
              "outflow_tx_count": 1
            }
          }
        }
      ],
      "total_inflow": 10784.7282,
      "total_outflow": 280216.1912,
      "net_flow": -269431.463
    },
    "GWEI": {
      "deployments": [
        {
          "chain": "ethereum",
          "contract": "0x2798b1cc5a993085e8a9d46e80499f1b63f42204",
          "exchange_flows": {
            "Bitget": {
              "inflow": 0.0,
              "outflow": 39268.9501,
              "net_flow": -39268.9501,
              "inflow_tx_count": 0,
              "outflow_tx_count": 1
            }
          }
        }
      ],
      "total_inflow": 0.0,
      "total_outflow": 39268.9501,
      "net_flow": -39268.9501
    },
    "SPACE": {
      "deployments": [
        {
          "chain": "ethereum",
          "contract": "0x87acFA3fD7A6e0d48677D070644D76905C2bDC00",
          "exchange_flows": {
            "Bitget": {
              "inflow": 256076.062,
              "outflow": 0.0,
              "net_flow": 256076.062,
              "inflow_tx_count": 2,
              "outflow_tx_count": 0
            },
            "Coinone": {
              "inflow": 1534.7286,
              "outflow": 0.0,
              "net_flow": 1534.7286,
              "inflow_tx_count": 1,
              "outflow_tx_count": 0
            },
            "GOPAX": {
              "inflow": 0.0,
              "outflow": 251430.0,
              "net_flow": -251430.0,
              "inflow_tx_count": 0,
              "outflow_tx_count": 1
            },
            "MEXC": {
              "inflow": 0.0,
              "outflow": 1195702.5,
              "net_flow": -1195702.5,
              "inflow_tx_count": 0,
              "outflow_tx_count": 1
            },
            "OKX": {
              "inflow": 2164348.65,
              "outflow": 0.0,
              "net_flow": 2164348.65,
              "inflow_tx_count": 2,
              "outflow_tx_count": 0
            },
            "Upbit": {
              "inflow": 0.0,
              "outflow": 6180.7906,
              "net_flow": -6180.7906,
              "inflow_tx_count": 0,
              "outflow_tx_count": 2
            }
          }
        },
        {
          "chain": "bsc",
          "contract": "0x87acFA3fD7A6e0d48677D070644D76905C2bDC00",
          "exchange_flows": {
            "Binance": {
              "inflow": 51428.6613,
              "outflow": 13634.9653,
              "net_flow": 37793.696,
              "inflow_tx_count": 2,
              "outflow_tx_count": 1
            }
          }
        }
      ],
      "total_inflow": 2473388.1019,
      "total_outflow": 1466948.2559,
      "net_flow": 1006439.846
    },
    "PUMP": {
      "deployments": [
        {
          "chain": "solana",
          "contract": "pumpCmXqMfrsAkQ5r49WcJnRayYRqmXz6ae8H7H9Dfn",
          "exchange_flows": {
            "Binance": {
              "inflow": 2880141.2748,
              "outflow": 45151087.31,
              "net_flow": -42270946.0352,
              "inflow_tx_count": 3,
              "outflow_tx_count": 6
            },
            "Bitvavo": {
              "inflow": 0.0,
              "outflow": 68744.0,
              "net_flow": -68744.0,
              "inflow_tx_count": 0,
              "outflow_tx_count": 1
            },
            "Bybit": {
              "inflow": 658217.0,
              "outflow": 2792949.571,
              "net_flow": -2134732.571,
              "inflow_tx_count": 3,
              "outflow_tx_count": 3
            },
            "Coinbase": {
              "inflow": 710099.17,
              "outflow": 382836.4278,
              "net_flow": 327262.7422,
              "inflow_tx_count": 2,
              "outflow_tx_count": 2
            },
            "Gate.io": {
              "inflow": 0.0,
              "outflow": 718601.17,
              "net_flow": -718601.17,
              "inflow_tx_count": 0,
              "outflow_tx_count": 1
            },
            "Kraken": {
              "inflow": 0.0,
              "outflow": 1012116.6,
              "net_flow": -1012116.6,
              "inflow_tx_count": 0,
              "outflow_tx_count": 4
            },
            "KuCoin": {
              "inflow": 113549.0,
              "outflow": 0.0,
              "net_flow": 113549.0,
              "inflow_tx_count": 1,
              "outflow_tx_count": 0
            },
            "MEXC": {
              "inflow": 10644922.08,
              "outflow": 0.0,
              "net_flow": 10644922.08,
              "inflow_tx_count": 2,
              "outflow_tx_count": 0
            },
            "Wintermute": {
              "inflow": 0.0,
              "outflow": 373368.4209,
              "net_flow": -373368.4209,
              "inflow_tx_count": 0,
              "outflow_tx_count": 3
            }
          }
        }
      ],
      "total_inflow": 15006928.5248,
      "total_outflow": 50499703.4997,
      "net_flow": -35492774.9749
    }
  }
}