{
  "timestamp": "2026-03-17T05:52:08Z",
  "lookback_seconds": 3600,
  "tokens": {
    "UAI": {
      "deployments": [
        {
          "chain": "bsc",
          "contract": "0x3e5d4f8aee0d9b3082d5f6da5d6e225d17ba9ea0",
          "exchange_flows": {
            "Binance": {
              "inflow": 0.0,
              "outflow": 455.1269,
              "net_flow": -455.1269,
              "inflow_tx_count": 0,
              "outflow_tx_count": 1
            }
          }
        }
      ],
      "total_inflow": 0.0,
      "total_outflow": 455.1269,
      "net_flow": -455.1269
    },
    "BIRB": {
      "deployments": [
        {
          "chain": "solana",
          "contract": "G7vQWurMkMMm2dU3iZpXYFTHT9Biio4F4gZCrwFpKNwG",
          "exchange_flows": {
            "Bitget": {
              "inflow": 121762.4489,
              "outflow": 0.0,
              "net_flow": 121762.4489,
              "inflow_tx_count": 1,
              "outflow_tx_count": 0
            },
            "Bybit": {
              "inflow": 245983.4489,
              "outflow": 230766.0489,
              "net_flow": 15217.4,
              "inflow_tx_count": 3,
              "outflow_tx_count": 2
            },
            "Coinbase": {
              "inflow": 109004.9,
              "outflow": 0.0,
              "net_flow": 109004.9,
              "inflow_tx_count": 1,
              "outflow_tx_count": 0
            },
            "Indodax": {
              "inflow": 0.0,
              "outflow": 6328.847,
              "net_flow": -6328.847,
              "inflow_tx_count": 0,
              "outflow_tx_count": 1
            },
            "KuCoin": {
              "inflow": 109003.6,
              "outflow": 109004.9,
              "net_flow": -1.3,
              "inflow_tx_count": 1,
              "outflow_tx_count": 1
            }
          }
        }
      ],
      "total_inflow": 585754.3978,
      "total_outflow": 346099.7959,
      "net_flow": 239654.6019
    },
    "AZTEC": {
      "deployments": [
        {
          "chain": "ethereum",
          "contract": "0xA27EC0006e59f245217Ff08CD52A7E8b169E62D2",
          "exchange_flows": {
            "Gate.io": {
              "inflow": 1562093.0,
              "outflow": 431962.4726,
              "net_flow": 1130130.5274,
              "inflow_tx_count": 1,
              "outflow_tx_count": 1
            },
            "HitBTC": {
              "inflow": 10171.6,
              "outflow": 9902.992,
              "net_flow": 268.608,
              "inflow_tx_count": 1,
              "outflow_tx_count": 1
            }
          }
        }
      ],
      "total_inflow": 1572264.6,
      "total_outflow": 441865.4646,
      "net_flow": 1130399.1354
    },
    "TRIA": {
      "deployments": [
        {
          "chain": "ethereum",
          "contract": "0x228bec415ade4b61d7caf0adf8c91eac587ba369",
          "exchange_flows": {
            "Bitget": {
              "inflow": 5747.6413,
              "outflow": 0.0,
              "net_flow": 5747.6413,
              "inflow_tx_count": 1,
              "outflow_tx_count": 0
            }
          }
        },
        {
          "chain": "bsc",
          "contract": "0xb0b92de23baa85fb06208277e925ced53edab482",
          "exchange_flows": {
            "Binance": {
              "inflow": 87626.2199,
              "outflow": 0.0,
              "net_flow": 87626.2199,
              "inflow_tx_count": 5,
              "outflow_tx_count": 0
            },
            "Bybit": {
              "inflow": 12135.6651,
              "outflow": 0.0,
              "net_flow": 12135.6651,
              "inflow_tx_count": 4,
              "outflow_tx_count": 0
            }
          }
        }
      ],
      "total_inflow": 105509.5263,
      "total_outflow": 0.0,
      "net_flow": 105509.5263
    },
    "SKR": {
      "deployments": [
        {
          "chain": "solana",
          "contract": "SKRbvo6Gf7GondiT3BbTfuRDPqLWei4j2Qy2NPGZhW3",
          "exchange_flows": {
            "Bybit": {
              "inflow": 0.0,
              "outflow": 665.5138,
              "net_flow": -665.5138,
              "inflow_tx_count": 0,
              "outflow_tx_count": 1
            },
            "Crypto.com": {
              "inflow": 39500.0,
              "outflow": 0.0,
              "net_flow": 39500.0,
              "inflow_tx_count": 1,
              "outflow_tx_count": 0
            }
          }
        }
      ],
      "total_inflow": 39500.0,
      "total_outflow": 665.5138,
      "net_flow": 38834.4862
    },
    "GWEI": {
      "deployments": [
        {
          "chain": "ethereum",
          "contract": "0x2798b1cc5a993085e8a9d46e80499f1b63f42204",
          "exchange_flows": {
            "KuCoin": {
              "inflow": 56.5704,
              "outflow": 0.0,
              "net_flow": 56.5704,
              "inflow_tx_count": 1,
              "outflow_tx_count": 0
            }
          }
        }
      ],
      "total_inflow": 56.5704,
      "total_outflow": 0.0,
      "net_flow": 56.5704
    },
    "SPACE": {
      "deployments": [
        {
          "chain": "ethereum",
          "contract": "0x87acFA3fD7A6e0d48677D070644D76905C2bDC00",
          "exchange_flows": {
            "Coinone": {
              "inflow": 1329.5018,
              "outflow": 0.0,
              "net_flow": 1329.5018,
              "inflow_tx_count": 1,
              "outflow_tx_count": 0
            },
            "Upbit": {
              "inflow": 0.0,
              "outflow": 1329.5018,
              "net_flow": -1329.5018,
              "inflow_tx_count": 0,
              "outflow_tx_count": 1
            }
          }
        },
        {
          "chain": "bsc",
          "contract": "0x87acFA3fD7A6e0d48677D070644D76905C2bDC00",
          "exchange_flows": {}
        }
      ],
      "total_inflow": 1329.5018,
      "total_outflow": 1329.5018,
      "net_flow": 0.0
    },
    "PUMP": {
      "deployments": [
        {
          "chain": "solana",
          "contract": "pumpCmXqMfrsAkQ5r49WcJnRayYRqmXz6ae8H7H9Dfn",
          "exchange_flows": {
            "Binance": {
              "inflow": 4692947.67,
              "outflow": 95661754.75,
              "net_flow": -90968807.08,
              "inflow_tx_count": 2,
              "outflow_tx_count": 6
            },
            "Bitget": {
              "inflow": 0.0,
              "outflow": 1473127.7148,
              "net_flow": -1473127.7148,
              "inflow_tx_count": 0,
              "outflow_tx_count": 1
            },
            "Bybit": {
              "inflow": 0.0,
              "outflow": 717033.6362,
              "net_flow": -717033.6362,
              "inflow_tx_count": 0,
              "outflow_tx_count": 1
            },
            "Coinbase": {
              "inflow": 0.0,
              "outflow": 448850.0643,
              "net_flow": -448850.0643,
              "inflow_tx_count": 0,
              "outflow_tx_count": 1
            },
            "Kraken": {
              "inflow": 653560.75,
              "outflow": 3194467.2,
              "net_flow": -2540906.45,
              "inflow_tx_count": 2,
              "outflow_tx_count": 2
            },
            "MEXC": {
              "inflow": 0.0,
              "outflow": 699049.0,
              "net_flow": -699049.0,
              "inflow_tx_count": 0,
              "outflow_tx_count": 1
            },
            "Wintermute": {
              "inflow": 60831722.9962,
              "outflow": 0.0,
              "net_flow": 60831722.9962,
              "inflow_tx_count": 4,
              "outflow_tx_count": 0
            }
          }
        }
      ],
      "total_inflow": 66178231.4162,
      "total_outflow": 102194282.3653,
      "net_flow": -36016050.9491
    }
  }
}