{
  "generated_at": "2026-03-20T16:32:28.058179+00:00",
  "tokens": {
    "AZTEC": {
      "cumulative_netflow": 103368777.815,
      "tge_date": "2025-07-01",
      "days_tracked": 38
    },
    "BIRB": {
      "cumulative_netflow": 25722485.0237,
      "tge_date": "2026-01-28",
      "days_tracked": 49
    },
    "GWEI": {
      "cumulative_netflow": 120091749.7258,
      "tge_date": "2026-02-05",
      "days_tracked": 41
    },
    "PUMP": {
      "cumulative_netflow": 19186773815.515,
      "tge_date": "2025-07-12",
      "days_tracked": 250
    },
    "SKR": {
      "cumulative_netflow": -16818588.3487,
      "tge_date": "2026-01-21",
      "days_tracked": 56
    },
    "SPACE": {
      "cumulative_netflow": 409046009.7507,
      "tge_date": "2026-01-29",
      "days_tracked": 48
    },
    "TRIA": {
      "cumulative_netflow": 94497108.6855,
      "tge_date": "2026-01-16",
      "days_tracked": 61
    },
    "UAI": {
      "cumulative_netflow": -2769962.5601,
      "tge_date": "2025-11-06",
      "days_tracked": 132
    }
  }
}