{
  "generated_at": "2026-03-19T02:57:44.141256+00:00",
  "tokens": {
    "AZTEC": {
      "cumulative_netflow": 89132136.0889,
      "tge_date": "2025-07-01",
      "days_tracked": 36
    },
    "BIRB": {
      "cumulative_netflow": 26241481.8485,
      "tge_date": "2026-01-28",
      "days_tracked": 47
    },
    "GWEI": {
      "cumulative_netflow": 117912312.5377,
      "tge_date": "2026-02-05",
      "days_tracked": 39
    },
    "PUMP": {
      "cumulative_netflow": 17868340674.1157,
      "tge_date": "2025-07-12",
      "days_tracked": 248
    },
    "SKR": {
      "cumulative_netflow": -15118985.3163,
      "tge_date": "2026-01-21",
      "days_tracked": 54
    },
    "SPACE": {
      "cumulative_netflow": 406563633.551,
      "tge_date": "2026-01-29",
      "days_tracked": 46
    },
    "TRIA": {
      "cumulative_netflow": 94068990.6453,
      "tge_date": "2026-01-16",
      "days_tracked": 59
    },
    "UAI": {
      "cumulative_netflow": -2539375.4511,
      "tge_date": "2025-11-06",
      "days_tracked": 130
    }
  }
}